enigma/__init__.py
enigma/keyfile.py
enigma/machine.py
enigma/main.py
enigma/plugboard.py
enigma/docs/source/conf.py
enigma/examples/example1.py
enigma/rotors/__init__.py
enigma/rotors/data.py
enigma/rotors/factory.py
enigma/rotors/rotor.py
enigma/tests/__init__.py
enigma/tests/test_enigma.py
enigma/tests/test_plugboard.py
enigma/tests/test_rotor.py
py_enigma-1.0.2.dist-info/licenses/LICENSE.txt
py_enigma-1.0.2.dist-info/METADATA
py_enigma-1.0.2.dist-info/WHEEL
py_enigma-1.0.2.dist-info/entry_points.txt
py_enigma-1.0.2.dist-info/top_level.txt
py_enigma-1.0.2.dist-info/RECORD
