Metadata-Version: 2.4
Name: py-enigma
Version: 1.0.2
Summary: A historically accurate Enigma machine simulation library.
Author-email: Brian Neal <bgneal@gmail.com>
License-Expression: MIT
Project-URL: Homepage, https://github.com/gremmie/enigma
Project-URL: Issues, https://github.com/gremmie/enigma/issues
Project-URL: Changelog, https://github.com/gremmie/enigma/blob/master/CHANGELOG.md
Keywords: crypto,cryptography,simulator,enigma,ww2,world war 2
Classifier: Development Status :: 5 - Production/Stable
Classifier: Environment :: Console
Classifier: Intended Audience :: End Users/Desktop
Classifier: Intended Audience :: Developers
Classifier: Intended Audience :: Information Technology
Classifier: Intended Audience :: Science/Research
Classifier: Intended Audience :: Other Audience
Classifier: Intended Audience :: Education
Classifier: Operating System :: OS Independent
Classifier: Natural Language :: English
Classifier: Programming Language :: Python
Classifier: Programming Language :: Python :: 3
Classifier: Topic :: Communications
Classifier: Topic :: Security
Classifier: Topic :: Security :: Cryptography
Classifier: Topic :: Software Development :: Libraries
Classifier: Topic :: Software Development :: Libraries :: Python Modules
Classifier: Topic :: Utilities
Requires-Python: >=3.2.2
License-File: LICENSE.txt
Dynamic: license-file
